{
	"names": {
		"default": {
			"roman": "Birdie"
		},
		"japan": {
			"roman": "Birdie",
			"original": "バーディー"
		}
	},
	"images": {
		"face": "birdie.webp"
	},
	"moves": {
		"{normalThrows}": [
			{
				"name": "Bull Spike",
				"input": "{close}, :b: {or} :f:+[MP] {or} [HP]"
			},
			{
				"name": "Bad Throw",
				"input": "{close}, :b: {or} :f:+[MK] {or} [HK]"
			}
		],
		"{uniqueAttacks}": [
			{
				"name": "Body Slam",
				"input": "{inAir} :d:+[HP]"
			}
		],
		"{specialMoves}": [
			{
				"name": "Bull Horn",
				"input": "{hold} [P]+[P] {or} [K]+[K] {then} {release}"
			},
			{
				"name": "Bull Head",
				"input": "{charge} :b: :f:+[P]"
			},
			{
				"name": "Murderer Chain",
				"input": ":360:+[P]"
			},
			{
				"name": "Bandit Chain",
				"input": ":360:+[K]"
			}
		],
		"{superCombos}": [
			{
				"name": "The Birdie",
				"input": "{charge} :b: :f::b::f:+[P]"
			},
			{
				"name": "Bull Revenger",
				"input": ":qcd::d::df:+[P] {or} [K]"
			}
		]
	}
}
